labb/__init__.py
labb/apps.py
labb/cli/__init__.py
labb/cli/handlers/__init__.py
labb/cli/handlers/build_handler.py
labb/cli/handlers/commons.py
labb/cli/handlers/components_handler.py
labb/cli/handlers/config_handler.py
labb/cli/handlers/init_handler.py
labb/cli/handlers/llms_handler.py
labb/cli/handlers/scan_handler.py
labb/cli/handlers/setup_handler.py
labb/cli/main.py
labb/cli/templates/input.template.css
labb/components/__init__.py
labb/components/registry.py
labb/components/schema/basics.yaml
labb/config.py
labb/contrib/__init__.py
labb/contrib/theme.py
labb/django_settings.py
labb/llms/__init__.py
labb/llms/file_operations.py
labb/llms/generator.py
labb/llms/llms.txt
labb/shortcuts.py
labb/templates/cotton/lb/accordion/index.html
labb/templates/cotton/lb/accordion/item.html
labb/templates/cotton/lb/alert/index.html
labb/templates/cotton/lb/avatar/group.html
labb/templates/cotton/lb/avatar/index.html
labb/templates/cotton/lb/badge/index.html
labb/templates/cotton/lb/button/index.html
labb/templates/cotton/lb/card/actions.html
labb/templates/cotton/lb/card/body.html
labb/templates/cotton/lb/card/figure.html
labb/templates/cotton/lb/card/index.html
labb/templates/cotton/lb/card/title.html
labb/templates/cotton/lb/checkbox/index.html
labb/templates/cotton/lb/diff/index.html
labb/templates/cotton/lb/diff/item-1.html
labb/templates/cotton/lb/diff/item-2.html
labb/templates/cotton/lb/diff/item_1.html
labb/templates/cotton/lb/diff/item_2.html
labb/templates/cotton/lb/diff/resizer.html
labb/templates/cotton/lb/drawer/checkbox.html
labb/templates/cotton/lb/drawer/content.html
labb/templates/cotton/lb/drawer/index.html
labb/templates/cotton/lb/drawer/overlay.html
labb/templates/cotton/lb/drawer/side.html
labb/templates/cotton/lb/drawer/toggle.html
labb/templates/cotton/lb/dropdown/content.html
labb/templates/cotton/lb/dropdown/index.html
labb/templates/cotton/lb/dropdown/trigger.html
labb/templates/cotton/lb/fab/close.html
labb/templates/cotton/lb/fab/index.html
labbui-0.1.0.dist-info/METADATA
labbui-0.1.0.dist-info/WHEEL
labbui-0.1.0.dist-info/entry_points.txt
labbui-0.1.0.dist-info/licenses/LICENSE
labbui-0.1.0.dist-info/RECORD
